<annotation>
	<folder>Kubis</folder>
	<filename>1_5.jpg</filename>
	<path>/home/royanmart/Documents/Bangkit 2021/Final Project/Dataset/Sementara/Kubis/1_5.jpg</path>
	<source>
		<database>Unknown</database>
	</source>
	<size>
		<width>1200</width>
		<height>1200</height>
		<depth>3</depth>
	</size>
	<segmented>0</segmented>
	<object>
		<name>Cabbage</name>
		<pose>Unspecified</pose>
		<truncated>0</truncated>
		<difficult>0</difficult>
		<bndbox>
			<xmin>351</xmin>
			<ymin>515</ymin>
			<xmax>849</xmax>
			<ymax>981</ymax>
		</bndbox>
	</object>
</annotation>
