<annotation><folder>open_images_volume</folder><filename>892069a06e9373b7.jpg</filename><path>/mnt/open_images_volume/892069a06e9373b7.jpg</path><source><database>Unknown</database></source><size><width>1024</width><height>512</height><depth>3</depth></size><segmented>0</segmented><object><name>Tomato</name><pose>Unspecified</pose><truncated>0</truncated><difficult>0</difficult><bndbox><xmin>297</xmin><ymin>0</ymin><xmax>520</xmax><ymax>175</ymax></bndbox></object><object><name>Tomato</name><pose>Unspecified</pose><truncated>0</truncated><difficult>0</difficult><bndbox><xmin>0</xmin><ymin>3</ymin><xmax>128</xmax><ymax>140</ymax></bndbox></object><object><name>Tomato</name><pose>Unspecified</pose><truncated>0</truncated><difficult>0</difficult><bndbox><xmin>150</xmin><ymin>0</ymin><xmax>318</xmax><ymax>137</ymax></bndbox></object></annotation>