<annotation>
	<folder>Pisang</folder>
	<filename>Banana0201.png</filename>
	<path>/home/royanmart/Documents/Bangkit 2021/Final Project/Done/Pisang/Banana0201.png</path>
	<source>
		<database>Unknown</database>
	</source>
	<size>
		<width>320</width>
		<height>258</height>
		<depth>3</depth>
	</size>
	<segmented>0</segmented>
	<object>
		<name>Pisang</name>
		<pose>Unspecified</pose>
		<truncated>1</truncated>
		<difficult>0</difficult>
		<bndbox>
			<xmin>1</xmin>
			<ymin>7</ymin>
			<xmax>106</xmax>
			<ymax>117</ymax>
		</bndbox>
	</object>
	<object>
		<name>Pisang</name>
		<pose>Unspecified</pose>
		<truncated>0</truncated>
		<difficult>0</difficult>
		<bndbox>
			<xmin>32</xmin>
			<ymin>28</ymin>
			<xmax>166</xmax>
			<ymax>97</ymax>
		</bndbox>
	</object>
	<object>
		<name>Pisang</name>
		<pose>Unspecified</pose>
		<truncated>0</truncated>
		<difficult>0</difficult>
		<bndbox>
			<xmin>44</xmin>
			<ymin>81</ymin>
			<xmax>204</xmax>
			<ymax>146</ymax>
		</bndbox>
	</object>
	<object>
		<name>Pisang</name>
		<pose>Unspecified</pose>
		<truncated>0</truncated>
		<difficult>0</difficult>
		<bndbox>
			<xmin>175</xmin>
			<ymin>40</ymin>
			<xmax>222</xmax>
			<ymax>216</ymax>
		</bndbox>
	</object>
	<object>
		<name>Pisang</name>
		<pose>Unspecified</pose>
		<truncated>0</truncated>
		<difficult>0</difficult>
		<bndbox>
			<xmin>23</xmin>
			<ymin>97</ymin>
			<xmax>174</xmax>
			<ymax>219</ymax>
		</bndbox>
	</object>
	<object>
		<name>Pisang</name>
		<pose>Unspecified</pose>
		<truncated>1</truncated>
		<difficult>0</difficult>
		<bndbox>
			<xmin>32</xmin>
			<ymin>138</ymin>
			<xmax>150</xmax>
			<ymax>258</ymax>
		</bndbox>
	</object>
</annotation>
